<root>
    <environment>
        <robot>
            <Polygon sortVertices="false">
                <Vertex x="-3" y="0.5"/>
                <Vertex x="-2" y="0.5"/>
                <Vertex x="-2" y="2"/>
                <Vertex x="-3" y="2"/>
            </Polygon>
        </robot>
        <obstacles>
            <Polygon sortVertices="false">
                <Vertex x="2.6599919766267339" y="-6.4374141684014372"/>
                <Vertex x="2.2365266097449901" y="-7.3166402687948775"/>
                <Vertex x="2.937608637578029" y="-7.3268282464741965"/>
                <Vertex x="5.6539231356094577" y="-8.1165858321822277"/>
                <Vertex x="9.2266805279213013" y="-11.00392668576653"/>
                <Vertex x="9.8888424795980683" y="-10.544738580810931"/>
                <Vertex x="5.9353072022848412" y="-8.0962263150255556"/>
                <Vertex x="6.1086683653698284" y="-6.8505020648867099"/>
                <Vertex x="4.5784110527203792" y="-3.8925371916069902"/>
                <Vertex x="3.6787616087504351" y="-5.6838071149783325"/>
                <Vertex x="0.66329857945001436" y="-6.0234187610051748"/>
            </Polygon>
            <Polygon sortVertices="false">
                <Vertex x="-11.877191664583531" y="-7.577309872986973"/>
                <Vertex x="-9.6253753938561708" y="-7.3679954002459755"/>
                <Vertex x="-10.590697952185534" y="-3.1597696005972113"/>
            </Polygon>
            <Polygon sortVertices="false">
                <Vertex x="-9.4569574494404502" y="5.1790311444838615"/>
                <Vertex x="-9.9430258760712071" y="4.1808160442653692"/>
                <Vertex x="-9.5993916140154081" y="3.8296390623239747"/>
                <Vertex x="-7.74973839154804" y="4.1939035671908211"/>
                <Vertex x="-5.7601925636518772" y="2.7083183579320718"/>
                <Vertex x="-5.0817292771918225" y="4.0530230569410115"/>
                <Vertex x="-6.9328412344321428" y="5.0279869482246093"/>
                <Vertex x="-8.1502559339972027" y="4.7033837840680146"/>
                <Vertex x="-8.405155954266613" y="4.8344747168714965"/>
                <Vertex x="-9.6490860206284079" y="6.0833937913442284"/>
                <Vertex x="-6.5727620887420919" y="6.8733534843860244"/>
                <Vertex x="-9.3464646093396286" y="7.7888283974504393"/>
                <Vertex x="-9.8801933393231103" y="8.9746036933391569"/>
                <Vertex x="-10.334688015819619" y="7.0165419648768346"/>
                <Vertex x="-11.156595355415359" y="5.6962851390262879"/>
                <Vertex x="-9.8677845292659665" y="6.0272348787663548"/>
            </Polygon>
            <Polygon sortVertices="false">
                <Vertex x="2.6797401235213121" y="5.8834198167239649"/>
                <Vertex x="1.8751444016687011" y="4.305263803546385"/>
                <Vertex x="1.5911603456267569" y="3.8695128860733488"/>
                <Vertex x="4.7388502438905489" y="5.1621248788997569"/>
                <Vertex x="5.4651440032853476" y="4.9478101218840136"/>
                <Vertex x="6.0379072291087512" y="7.2974714468919064"/>
                <Vertex x="5.1174081116261485" y="7.744226714772747"/>
                <Vertex x="3.670382260772596" y="7.2909305945461158"/>
                <Vertex x="1.7900865514532751" y="9.627353078367987"/>
                <Vertex x="1.9717337438010654" y="7.0575786744541"/>
            </Polygon>
            <Polygon sortVertices="false">
                <Vertex x="-4.1296318442614766" y="4.3847137648844754"/>
                <Vertex x="-3.7381239835643569" y="3.4963612140540867"/>
                <Vertex x="0.027190872437145686" y="7.3629354459248049"/>
                <Vertex x="-3.9490326556068904" y="9.0000634344349297"/>
            </Polygon>
            <Polygon sortVertices="false">
                <Vertex x="6.1665139766076456" y="1.2845450803508243"/>
                <Vertex x="7.8962842701711935" y="0.96697386695184129"/>
                <Vertex x="11.12894286006785" y="1.4580733055091173"/>
                <Vertex x="9.0617888097417438" y="5.1481889002992958"/>
            </Polygon>
            <Polygon sortVertices="false">
                <Vertex x="7.1219928809188868" y="-6.8825207608279388"/>
                <Vertex x="8.422706057619969" y="-6.396424164508649"/>
                <Vertex x="9.3885805696766482" y="-6.0192622606830017"/>
                <Vertex x="9.7982645382514715" y="-5.6918375187018775"/>
                <Vertex x="10.475619383324403" y="-2.9843333126012643"/>
                <Vertex x="8.5944566909147877" y="-4.6745865053597848"/>
                <Vertex x="7.7598447273067048" y="-4.2494441450383782"/>
                <Vertex x="7.6359104713090051" y="-5.1367474456705642"/>
            </Polygon>
            <Polygon sortVertices="false">
                <Vertex x="-1.2432217842059625" y="-8.7250014685148045"/>
                <Vertex x="2.286595664176085" y="-9.05418571236582"/>
                <Vertex x="3.309083723563492" y="-8.2187723564223383"/>
                <Vertex x="0.3541296092784032" y="-5.9436039415965398"/>
            </Polygon>
        </obstacles>
        <mapSize>30</mapSize>
    </environment>
    <plannerSettings>
        <start>
            <Vertex x="-12.295836543402007" y="12.295836543402007" theta="0" thetaLb="0" thetaUb="0"/>
        </start>
        <goal>
            <Vertex x="12.295836543402007" y="-12.295836543402007" theta="0" thetaLb="0" thetaUb="0"/>
        </goal>
    </plannerSettings>
</root>
